sixrunr/__init__.py
sixrunr/cwlrunr.py
sixrunr/utils.py
sixrunr-0.1.3.dist-info/LICENSE
sixrunr-0.1.3.dist-info/METADATA
sixrunr-0.1.3.dist-info/WHEEL
sixrunr-0.1.3.dist-info/entry_points.txt
sixrunr-0.1.3.dist-info/top_level.txt
sixrunr-0.1.3.dist-info/RECORD
